CHANGES
LICENSE
MANIFEST.in
README.rst
REQUIREMENTS.txt
setup.cfg
setup.py
CallerLookup/Configuration.py
CallerLookup/CountryCodes.py
CallerLookup/Main.py
CallerLookup/Responses.py
CallerLookup/Sample.py
CallerLookup/Search.py
CallerLookup/Strings.py
CallerLookup/__init__.py
CallerLookup.egg-info/PKG-INFO
CallerLookup.egg-info/SOURCES.txt
CallerLookup.egg-info/dependency_links.txt
CallerLookup.egg-info/requires.txt
CallerLookup.egg-info/top_level.txt