Metadata-Version: 1.1
Name: CallerLookup
Version: 1.2.93
Summary: Reverse Caller Identity
Home-page: http://github.com/scottphilip/caller-lookup
Author: Scott Philip
Author-email: sp@scottphilip.com
License: GNU (v3) License
Keywords: Reverse Caller Identity,TrueCaller
Platform: UNKNOWN
Classifier: Environment :: Web Environment
Classifier: Intended Audience :: Developers
Classifier: Operating System :: OS Independent
Classifier: Programming Language :: Python
Classifier: Programming Language :: Python :: 2.7
Classifier: Programming Language :: Python :: 3.3
Classifier: Programming Language :: Python :: 3.4
Classifier: Programming Language :: Python :: 3.5
Classifier: Programming Language :: Python :: 3.6
